aioipfabric/__init__.py
aioipfabric/aiofut.py
aioipfabric/api.py
aioipfabric/base_client.py
aioipfabric/client.py
aioipfabric/consts.py
aioipfabric/filters.py
aioipfabric/mixins/__init__.py
aioipfabric/mixins/cabling.py
aioipfabric/mixins/configs.py
aioipfabric/mixins/diagrams.py
aioipfabric/mixins/diagramsV4.py
aioipfabric/mixins/inventory.py
aioipfabric/mixins/portchan.py
aioipfabric/table_api.py
aio_ipfabric-1.0.0.dist-info/WHEEL
aio_ipfabric-1.0.0.dist-info/METADATA
aio_ipfabric-1.0.0.dist-info/RECORD
