Metadata-Version: 2.1
Name: aio-ipfabric
Version: 1.0.0
Summary: IP Fabric asyncio client
Author: Jeremy Schulman
Author-email: nwkautomaniac@gmail.com
Requires-Python: >=3.8.1,<4.0
Classifier: Programming Language :: Python :: 3
Classifier: Programming Language :: Python :: 3.9
Classifier: Programming Language :: Python :: 3.10
Classifier: Programming Language :: Python :: 3.11
Requires-Dist: httpx (>=0.23.1,<0.24.0)
Requires-Dist: parsimonious (>=0.10.0,<0.11.0)
Requires-Dist: tenacity (>=8.1.0,<9.0.0)
